bdxmail/__init__.py
bdxmail/bdxmail.py
bdxmail-0.0.1.dist-info/LICENSE
bdxmail-0.0.1.dist-info/METADATA
bdxmail-0.0.1.dist-info/WHEEL
bdxmail-0.0.1.dist-info/entry_points.txt
bdxmail-0.0.1.dist-info/top_level.txt
bdxmail-0.0.1.dist-info/RECORD
