Metadata-Version: 2.1
Name: bdxmail
Version: 0.0.1
Summary: BD EMAIL BOMBER
Home-page: https://github.com/AKXVAU
Author: AKXVAU
Author-email: bdXsms69@gmail.com
License: MIT
Keywords: hacker,spam,tool,fmail,bomber,call,prank,termux,hack,fmail bomber,fmail bomber,AKXVAU,bdxfmail,xbomber,bdsms.ml,python,python fmail,python bomber,python spam,inbox killer,inbox,killmail,bdxmail
Platform: UNKNOWN
Classifier: Development Status :: 4 - Beta
Classifier: Intended Audience :: Developers
Classifier: Topic :: Software Development :: Libraries :: Python Modules
Classifier: License :: OSI Approved :: MIT License
Classifier: Programming Language :: Python :: 3
Classifier: Operating System :: OS Independent
Classifier: Environment :: Console
Requires-Python: >=3.9
License-File: LICENSE
Requires-Dist: lolcat
Requires-Dist: requests
